h2o/__init__.py
h2o/assembly.py
h2o/astfun.py
h2o/buildinfo.txt
h2o/cross_validation.py
h2o/demos.py
h2o/display.py
h2o/exceptions.py
h2o/expr.py
h2o/expr_optimizer.py
h2o/frame.py
h2o/group_by.py
h2o/h2o.py
h2o/job.py
h2o/two_dim_table.py
h2o/version.txt
h2o/automl/__init__.py
h2o/automl/autoh2o.py
h2o/backend/__init__.py
h2o/backend/cluster.py
h2o/backend/connection.py
h2o/backend/server.py
h2o/estimators/__init__.py
h2o/estimators/aggregator.py
h2o/estimators/deeplearning.py
h2o/estimators/deepwater.py
h2o/estimators/estimator_base.py
h2o/estimators/gbm.py
h2o/estimators/glm.py
h2o/estimators/glrm.py
h2o/estimators/kmeans.py
h2o/estimators/naive_bayes.py
h2o/estimators/pca.py
h2o/estimators/random_forest.py
h2o/estimators/stackedensemble.py
h2o/estimators/svd.py
h2o/estimators/word2vec.py
h2o/estimators/xgboost.py
h2o/grid/__init__.py
h2o/grid/grid_search.py
h2o/grid/metrics.py
h2o/model/__init__.py
h2o/model/autoencoder.py
h2o/model/binomial.py
h2o/model/clustering.py
h2o/model/confusion_matrix.py
h2o/model/dim_reduction.py
h2o/model/metrics_base.py
h2o/model/model_base.py
h2o/model/model_builder.py
h2o/model/model_future.py
h2o/model/multinomial.py
h2o/model/ordinal.py
h2o/model/regression.py
h2o/model/word_embedding.py
h2o/schemas/__init__.py
h2o/schemas/error.py
h2o/transforms/__init__.py
h2o/transforms/decomposition.py
h2o/transforms/preprocessing.py
h2o/transforms/transform_base.py
h2o/utils/__init__.py
h2o/utils/backward_compatibility.py
h2o/utils/compatibility.py
h2o/utils/config.py
h2o/utils/debugging.py
h2o/utils/progressbar.py
h2o/utils/shared_utils.py
h2o/utils/typechecks.py
h2o_pysparkling_2.1-2.1.28.dist-info/METADATA
h2o_pysparkling_2.1-2.1.28.dist-info/RECORD
h2o_pysparkling_2.1-2.1.28.dist-info/WHEEL
h2o_pysparkling_2.1-2.1.28.dist-info/top_level.txt
py_sparkling/__init__.py
py_sparkling/ml/__init__.py
py_sparkling/ml/algos.py
py_sparkling/ml/features.py
py_sparkling/ml/models.py
pysparkling/__init__.py
pysparkling/conf.py
pysparkling/context.py
pysparkling/conversions.py
pysparkling/initializer.py
pysparkling/version.txt
